LICENSE
fcmeans/__init__.py
fcmeans/cli.py
fcmeans/main.py
fuzzy_c_means-1.7.0.dist-info/entry_points.txt
fuzzy_c_means-1.7.0.dist-info/LICENSE
fuzzy_c_means-1.7.0.dist-info/WHEEL
fuzzy_c_means-1.7.0.dist-info/METADATA
fuzzy_c_means-1.7.0.dist-info/RECORD
