Metadata-Version: 2.1
Name: fuzzy-c-means
Version: 1.7.0
Summary: A simple python implementation of Fuzzy C-means algorithm.
Home-page: https://github.com/omadson/fuzzy-c-means
License: MIT
Keywords: machine-learning,data-science,fuzzy-c-means,clustering
Author: Madson Dias
Author-email: madsonddias@gmail.com
Requires-Python: >=3.9,<4.0
Classifier: License :: OSI Approved :: MIT License
Classifier: Operating System :: OS Independent
Classifier: Programming Language :: Python :: 3
Classifier: Programming Language :: Python :: 3.9
Classifier: Programming Language :: Python :: 3.10
Classifier: Programming Language :: Python :: 3.11
Classifier: Topic :: Software Development :: Libraries :: Python Modules
Requires-Dist: joblib (>=1.2.0,<2.0.0)
Requires-Dist: numpy (>=1.21.1,<2.0.0)
Requires-Dist: pydantic (>=1.9.0,<2.0.0)
Requires-Dist: tabulate (>=0.8.9,<0.9.0)
Requires-Dist: tqdm (>=4.64.1,<5.0.0)
Requires-Dist: typer (>=0.4.0,<0.5.0)
Project-URL: Documentation, https://fuzzy-c-means.readthedocs.io/en/latest/
Project-URL: Repository, https://github.com/omadson/fuzzy-c-means
